{
  "active_days": 1,
  "day_info": [
    {
      "active_time": {
        "hr": 9,
        "min": 43
      },
      "rest_time": {
        "hr": 2,
        "min": 28
      },
      "distance": {
        "route": 15.2,
        "up": 1219,
        "down": 1224
      },
      "check_point": [
        {
          "type": 1,
          "stay_time": [
            "09:04"
          ]
        },
        {
          "spot_name": "筑前深江駅",
          "type": 5,
          "next_point_time": {
            "hr": 2,
            "min": 48
          },
          "stay_time": [
            "09:04",
            "09:05"
          ]
        },
        {
          "spot_name": "二丈岳",
          "type": 5,
          "next_point_time": {
            "hr": 0,
            "min": 32
          },
          "stay_time": [
            "11:54",
            "12:38"
          ]
        },
        {
          "spot_name": "真名子登山口",
          "type": 5,
          "next_point_time": {
            "hr": 0,
            "min": 22
          },
          "stay_time": [
            "13:11",
            "13:12"
          ]
        },
        {
          "spot_name": "女岳北登山口",
          "type": 5,
          "next_point_time": {
            "hr": 0,
            "min": 36
          },
          "stay_time": [
            "13:35",
            "13:40"
          ]
        },
        {
          "spot_name": "女岳",
          "type": 5,
          "next_point_time": {
            "hr": 0,
            "min": 23
          },
          "stay_time": [
            "14:16",
            "14:40"
          ]
        },
        {
          "spot_name": "女岳北登山口",
          "type": 5,
          "next_point_time": {
            "hr": 0,
            "min": 21
          },
          "stay_time": [
            "15:04",
            "15:08"
          ]
        },
        {
          "spot_name": "真名子登山口",
          "type": 5,
          "next_point_time": {
            "hr": 0,
            "min": 10
          },
          "stay_time": [
            "15:29",
            "15:30"
          ]
        },
        {
          "spot_name": "加茂神社",
          "type": 5,
          "next_point_time": {
            "hr": 0,
            "min": 52
          },
          "stay_time": [
            "15:41",
            "15:43"
          ]
        },
        {
          "spot_name": "加茂ゆらりんこ橋登山口",
          "type": 5,
          "next_point_time": {
            "hr": 2,
            "min": 4
          },
          "stay_time": [
            "16:36",
            "16:42"
          ]
        },
        {
          "spot_name": "大入駅",
          "type": 4,
          "stay_time": [
            "18:47"
          ]
        },
        {
          "type": 2,
          "stay_time": [
            "18:47"
          ]
        }
      ]
    }
  ]
}